plotcap/__init__.py
plotcap/api.py
plotcap/cli.py
plotcap/mac_address.py
plotcap/plotting.py
plotcap-1.3.1.dist-info/AUTHORS.rst
plotcap-1.3.1.dist-info/LICENSE.txt
plotcap-1.3.1.dist-info/METADATA
plotcap-1.3.1.dist-info/WHEEL
plotcap-1.3.1.dist-info/entry_points.txt
plotcap-1.3.1.dist-info/RECORD
