Metadata-Version: 2.3
Name: plotcap
Version: 1.3.1
Summary: PlotCap - a simple network visualization tool
License: MIT
Keywords: pcap,network
Author: Darknet ehf
Author-email: info@labs.darknet.com
Maintainer: Darknet ehf
Maintainer-email: info@labs.darknet.com
Requires-Python: >=3.10,<4
Classifier: Topic :: System :: Networking
Classifier: Topic :: System :: Networking :: Monitoring
Classifier: Topic :: Security
Classifier: Topic :: Scientific/Engineering :: Visualization
Requires-Dist: netaddr (>=1.3.0,<2.0.0)
Requires-Dist: netgraph (>=4.13.2,<5.0.0)
Requires-Dist: networkx (>=3.4.2,<4.0.0)
Requires-Dist: pyvis (>=0.3.2,<0.4.0)
Requires-Dist: pyyaml (>=6.0.2,<7.0.0)
Requires-Dist: scapy (>=2.6.1,<3.0.0)
Project-URL: Bug Tracker, https://github.com/darknetehf/plotcap/issues
Project-URL: Documentation, https://github.com/darknetehf/plotcap
Project-URL: Homepage, https://github.com/darknetehf/plotcap
Project-URL: Repository, https://github.com/darknetehf/plotcap
